MSDSF21M0533_Package/__init__.py
MSDSF21M0533_Package/logic_gates.py
MSDSF21M0533_Package/speedometer.py
moanas001-0.0.1.dist-info/LICENSE
moanas001-0.0.1.dist-info/METADATA
moanas001-0.0.1.dist-info/WHEEL
moanas001-0.0.1.dist-info/top_level.txt
moanas001-0.0.1.dist-info/RECORD
