Metadata-Version: 2.1
Name: moanas001
Version: 0.0.1
Summary: PythonTutorial
Author: Muhammad Anas
Author-email: msdsf21m533@pucit.edu.pk
Keywords: python,logic gates,binary as string,speedometer
Classifier: Development Status :: 1 - Planning
Classifier: Intended Audience :: Developers
Classifier: Programming Language :: Python :: 3
Classifier: Operating System :: Unix
Classifier: Operating System :: MacOS :: MacOS X
Classifier: Operating System :: Microsoft :: Windows
License-File: LICENSE
